polarimetry/__init__.py
polarimetry/data.py
polarimetry/function.py
polarimetry/io.py
polarimetry/plot.py
polarimetry/py.typed
polarimetry/version.py
polarimetry/lhcb/__init__.py
polarimetry/lhcb/dynamics.py
polarimetry/lhcb/model-definitions.yaml
polarimetry/lhcb/particle-definitions.yaml
polarimetry/lhcb/particle.py
polarimetry/lhcb/symbol.py
polarimetry_lc2pkpi-0.1.0.dist-info/licenses/LICENSE
polarimetry_lc2pkpi-0.1.0.dist-info/METADATA
polarimetry_lc2pkpi-0.1.0.dist-info/WHEEL
polarimetry_lc2pkpi-0.1.0.dist-info/top_level.txt
polarimetry_lc2pkpi-0.1.0.dist-info/RECORD
