Metadata-Version: 2.4
Name: polarimetry-lc2pkpi
Version: 0.1.0
Summary: Symbolic expressions that describe an aligned polarimeter vector field
Author: Mikhail Mikhasenko, Remco de Boer
License:                                  Apache License
Classifier: Development Status :: 4 - Beta
Classifier: Intended Audience :: Developers
Classifier: Intended Audience :: Education
Classifier: Intended Audience :: Science/Research
Classifier: License :: OSI Approved :: Apache Software License
Classifier: Natural Language :: English
Classifier: Operating System :: OS Independent
Classifier: Programming Language :: Python :: 3.10
Classifier: Programming Language :: Python :: 3.11
Classifier: Programming Language :: Python :: 3.12
Classifier: Programming Language :: Python :: 3.13
Classifier: Programming Language :: Python :: 3.14
Classifier: Programming Language :: Python
Classifier: Topic :: Scientific/Engineering :: Physics
Classifier: Topic :: Scientific/Engineering
Classifier: Typing :: Typed
Requires-Python: >=3.10
License-File: LICENSE
Requires-Dist: IPython
Requires-Dist: PyYAML
Requires-Dist: ampform>=0.15.11
Requires-Dist: ampform-dpd~=0.3.0
Requires-Dist: attrs>=20.1.0
Requires-Dist: cairosvg
Requires-Dist: matplotlib
Requires-Dist: numpy
Requires-Dist: scour
Requires-Dist: sympy>=1.10
Requires-Dist: tensorwaves[jax]>=0.4.5
Dynamic: license-file
